CHANGELOG.md
LICENSE
MANIFEST.in
README.md
setup.py
cortex/__init__.py
cortex/action.py
cortex/agent.py
cortex/build.py
cortex/camel.py
cortex/client.py
cortex/connection.py
cortex/dataset.py
cortex/env.py
cortex/exceptions.py
cortex/experiment.py
cortex/logger.py
cortex/magics.py
cortex/message.py
cortex/pipeline.py
cortex/pipeline_loader.py
cortex/profile.py
cortex/properties.py
cortex/run.py
cortex/schema.py
cortex/session.py
cortex/skill.py
cortex/timer.py
cortex/utils.py
cortex/viz.py
cortex/builder/__init__.py
cortex/builder/action_builder.py
cortex/builder/builder_factory.py
cortex/builder/connection_builder.py
cortex/builder/dataset_builder.py
cortex/builder/declared_attributes_builder.py
cortex/builder/docker_image_builder.py
cortex/builder/profile_builder.py
cortex/builder/schema_builder.py
cortex/builder/skill_builder.py
cortex/builder/resources/Dockerfile.daemon.j2
cortex/builder/resources/Dockerfile.func.j2
cortex/builder/resources/Dockerfile.job.j2
cortex/builder/resources/__init__.py
cortex/builder/resources/daemon.py.j2
cortex/builder/resources/func.py.j2
cortex/builder/resources/job.py.j2
cortex/builder/resources/predict_function_sklearn.py.j2
cortex/builder/utils/__init__.py
cortex/builder/utils/docker_utils.py
cortex/builder/utils/python_utils.py
cortex/builder/utils/template_utils.py
cortex_client/__init__.py
cortex_client/actionclient.py
cortex_client/agentclient.py
cortex_client/authenticationclient.py
cortex_client/builderclient.py
cortex_client/cache.py
cortex_client/catalogclient.py
cortex_client/client.py
cortex_client/connectionclient.py
cortex_client/datasetsclient.py
cortex_client/experimentclient.py
cortex_client/jobsclient.py
cortex_client/modelclient.py
cortex_client/modelcontext.py
cortex_client/modelprocess.py
cortex_client/modelrouter.py
cortex_client/modelrunner.py
cortex_client/profilesclient.py
cortex_client/secretsclient.py
cortex_client/serviceconnector.py
cortex_client/sessionclient.py
cortex_client/types.py
cortex_client.egg-info/PKG-INFO
cortex_client.egg-info/SOURCES.txt
cortex_client.egg-info/dependency_links.txt
cortex_client.egg-info/entry_points.txt
cortex_client.egg-info/requires.txt
cortex_client.egg-info/top_level.txt
