Metadata-Version: 2.1
Name: cortex-client
Version: 7.1.2
Summary: [Deprecated] Python SDK for the CognitiveScale Cortex5 AI Platform
Home-page: https://docs.cortex.insights.ai
Author: CognitiveScale
Author-email: info@cognitivescale.com
License: CognitiveScale Inc.
Platform: linux
Platform: osx
Classifier: Operating System :: MacOS :: MacOS X
Classifier: Operating System :: POSIX
Classifier: Programming Language :: Python :: 3.6
Provides-Extra: viz
